quartet_epcis/__init__.py
quartet_epcis/admin.py
quartet_epcis/apps.py
quartet_epcis/filters.py
quartet_epcis/renderers.py
quartet_epcis/routers.py
quartet_epcis/serializers.py
quartet_epcis/urls.py
quartet_epcis/views.py
quartet_epcis/viewsets.py
quartet_epcis/db_api/__init__.py
quartet_epcis/db_api/queries.py
quartet_epcis/management/__init__.py
quartet_epcis/management/commands/__init__.py
quartet_epcis/management/commands/create_epcis_groups.py
quartet_epcis/management/commands/create_epcis_rule.py
quartet_epcis/management/commands/remove_event_data.py
quartet_epcis/migrations/0001_initial.py
quartet_epcis/migrations/0002_auto_20180718_1528.py
quartet_epcis/migrations/0003_auto_20181031_1420.py
quartet_epcis/migrations/0004_auto_20190812_1630.py
quartet_epcis/migrations/0005_auto_20200902_1023.py
quartet_epcis/migrations/0006_alter_businesstransaction_id_and_more.py
quartet_epcis/migrations/__init__.py
quartet_epcis/models/__init__.py
quartet_epcis/models/abstractmodels.py
quartet_epcis/models/choices.py
quartet_epcis/models/entries.py
quartet_epcis/models/events.py
quartet_epcis/models/headers.py
quartet_epcis/parsing/__init__.py
quartet_epcis/parsing/business_parser.py
quartet_epcis/parsing/context_parser.py
quartet_epcis/parsing/errors.py
quartet_epcis/parsing/json.py
quartet_epcis/parsing/parser.py
quartet_epcis/parsing/steps.py
quartet_epcis-4.0.0.dist-info/AUTHORS.rst
quartet_epcis-4.0.0.dist-info/LICENSE
quartet_epcis-4.0.0.dist-info/METADATA
quartet_epcis-4.0.0.dist-info/WHEEL
quartet_epcis-4.0.0.dist-info/top_level.txt
quartet_epcis-4.0.0.dist-info/RECORD
