Metadata-Version: 2.1
Name: quartet-epcis
Version: 4.0.0
Summary: Defines EPCIS models and XML parsing.
Home-page: https://gitlab.com/serial-lab/quartet_epcis
Author: Rob Magee
Author-email: slab@serial-lab.com
License: GPLv3
Keywords: seriallab quartet_epcis epcis level-4 quartet
Platform: UNKNOWN
Classifier: Development Status :: 5 - Production/Stable
Classifier: Framework :: Django
Classifier: Framework :: Django :: 2.0
Classifier: Intended Audience :: Healthcare Industry
Classifier: Intended Audience :: Manufacturing
Classifier: Intended Audience :: Developers
Classifier: License :: OSI Approved :: GNU Affero General Public License v3 or later (AGPLv3+)
Classifier: Natural Language :: English
Classifier: Programming Language :: Python :: 3
Classifier: Programming Language :: Python :: 3.5
Classifier: Programming Language :: Python :: 3.6
Requires-Python: ~=3.5
Requires-Dist: eparsecis
Requires-Dist: EPCPyYes
Requires-Dist: django-model-utils
Requires-Dist: python-dateutil
